wsadmin_type_hints/__init__.py
wsadmin_type_hints/core/AdminApp.py
wsadmin_type_hints/core/AdminConfig.py
wsadmin_type_hints/core/AdminControl.py
wsadmin_type_hints/core/AdminTask.py
wsadmin_type_hints/core/Help.py
wsadmin_type_hints/core/__init__.py
wsadmin_type_hints/scripting/AdminApplication.py
wsadmin_type_hints/scripting/AdminAuthorizations.py
wsadmin_type_hints/scripting/AdminBLA.py
wsadmin_type_hints/scripting/AdminClusterManagement.py
wsadmin_type_hints/scripting/AdminJ2C.py
wsadmin_type_hints/scripting/AdminJDBC.py
wsadmin_type_hints/scripting/AdminJMS.py
wsadmin_type_hints/scripting/AdminLibHelp.py
wsadmin_type_hints/scripting/AdminNodeGroupManagement.py
wsadmin_type_hints/scripting/AdminNodeManagement.py
wsadmin_type_hints/scripting/AdminResources.py
wsadmin_type_hints/scripting/AdminServerManagement.py
wsadmin_type_hints/scripting/AdminUtilities.py
wsadmin_type_hints/scripting/__init__.py
wsadmin_type_hints/typing_objects/__init__.py
wsadmin_type_hints/typing_objects/object_name.py
wsadmin_type_hints/typing_objects/object_types.py
wsadmin_type_hints/typing_objects/wsadmin_types.py
wsadmin_type_hints-0.3.0.dist-info/LICENSE
wsadmin_type_hints-0.3.0.dist-info/WHEEL
wsadmin_type_hints-0.3.0.dist-info/METADATA
wsadmin_type_hints-0.3.0.dist-info/RECORD
