Metadata-Version: 2.1
Name: wsadmin-type-hints
Version: 0.3.0
Summary: Provide type hints for `wsadmin` object methods
Home-page: https://lukesavefrogs.github.io/wsadmin-type-hints/
License: MIT
Keywords: wsadmin,ibm,stubs,types,jython,autocompletion,intellisense
Author: Luca Salvarani
Author-email: lucasalvarani99@gmail.com
Requires-Python: >=3.8,<=3.11
Classifier: License :: OSI Approved :: MIT License
Classifier: Programming Language :: Python :: 3
Classifier: Programming Language :: Python :: 3.8
Classifier: Programming Language :: Python :: 3.9
Classifier: Programming Language :: Python :: 3.10
Classifier: Programming Language :: Python :: 3.11
Project-URL: Bug Tracker, https://github.com/LukeSavefrogs/wsadmin-type-hints/issues
Project-URL: Documentation, https://lukesavefrogs.github.io/wsadmin-type-hints/
Project-URL: Repository, https://github.com/LukeSavefrogs/wsadmin-type-hints/
